LICENSE
MANIFEST.in
README.rst
helga_reviewboard.py
setup.py
helga_reviewboard.egg-info/PKG-INFO
helga_reviewboard.egg-info/SOURCES.txt
helga_reviewboard.egg-info/dependency_links.txt
helga_reviewboard.egg-info/entry_points.txt
helga_reviewboard.egg-info/top_level.txt
helga_reviewboard.egg-info/zip-safe